Metadata-Version: 2.4
Name: megabouts
Version: 0.1.2
Summary: Megabouts: a toolbox to quantify zebrafish locomotion
Author-email: Adrien Jouary <adrien.jouary@research.fchampalimaud.org>
License: # Non-Commercial Research and Academic Use Software License and Terms of Use
Project-URL: Homepage, https://megabouts.ai
Project-URL: Documentation, https://megabouts.ai
Project-URL: Repository, https://github.com/orger-lab/megabouts.git
Project-URL: Issues, https://github.com/orger-lab/megabouts/issues
Classifier: Development Status :: 3 - Alpha
Classifier: Intended Audience :: Science/Research
Classifier: Topic :: Scientific/Engineering :: Artificial Intelligence
Classifier: License :: Other/Proprietary License
Classifier: Programming Language :: Python :: 3
Requires-Python: ~=3.11
License-File: LICENSE.md
Requires-Dist: ipykernel
Requires-Dist: h5py
Requires-Dist: matplotlib
Requires-Dist: numpy==1.26.4
Requires-Dist: pandas
Requires-Dist: scipy
Requires-Dist: scikit-image
Requires-Dist: pybaselines
Requires-Dist: scikit-learn
Requires-Dist: torch
Requires-Dist: sporco
Provides-Extra: test
Requires-Dist: pytest; extra == "test"
Requires-Dist: nbmake; extra == "test"
Provides-Extra: dev
Requires-Dist: pre-commit; extra == "dev"
Requires-Dist: ruff; extra == "dev"
Provides-Extra: docs
Requires-Dist: build; extra == "docs"
Requires-Dist: twine; extra == "docs"
Requires-Dist: setuptools; extra == "docs"
Requires-Dist: sphinx>=5.0.0; extra == "docs"
Requires-Dist: sphinx_design; extra == "docs"
Requires-Dist: pydata-sphinx-theme; extra == "docs"
Requires-Dist: sphinx-autobuild; extra == "docs"
Requires-Dist: myst-nb; extra == "docs"
Requires-Dist: sphinx-autoapi; extra == "docs"
Requires-Dist: sphinxcontrib-video; extra == "docs"
Requires-Dist: sphinxcontrib-jupyter; extra == "docs"
Requires-Dist: sphinx-togglebutton; extra == "docs"
Requires-Dist: sphinx-gallery; extra == "docs"
Requires-Dist: sphinx-tabs; extra == "docs"
Dynamic: license-file
